liquipydia/__init__.py
liquipydia-0.0.1.dist-info/LICENSE
liquipydia-0.0.1.dist-info/METADATA
liquipydia-0.0.1.dist-info/WHEEL
liquipydia-0.0.1.dist-info/top_level.txt
liquipydia-0.0.1.dist-info/RECORD
